gitsafe.py
gitsafe-0.1.0.dist-info/LICENSE
gitsafe-0.1.0.dist-info/METADATA
gitsafe-0.1.0.dist-info/WHEEL
gitsafe-0.1.0.dist-info/entry_points.txt
gitsafe-0.1.0.dist-info/top_level.txt
gitsafe-0.1.0.dist-info/RECORD
