Metadata-Version: 2.1
Name: gitsafe
Version: 0.1.0
Summary: A tool to keep copies (aka backups) of git repositories.
Home-page: https://github.com/tammann/gitsafe
Author: Tobias Ammann
Author-email: tammann@ergonomics.ch
License: MIT
Platform: UNKNOWN
Requires-Dist: colorama
Requires-Dist: SQLObject
Requires-Dist: sh
Requires-Dist: tabulate
Requires-Dist: tqdm
Requires-Dist: typer
Provides-Extra: dev
Requires-Dist: black ; extra == 'dev'
Requires-Dist: wheel ; extra == 'dev'
Requires-Dist: twine ; extra == 'dev'
